{"name":"validar  segundo cambio  de apps $4990","id":"segundo-cambio-de-apps;validar--segundo-cambio--de-apps-$4990","testSteps":[{"number":1,"description":"Dado que el usuario haga el primer cambio con cobro","duration":19381,"startTime":"2023-01-24T12:56:08.757472100-05:00[America/Bogota]","screenshots":[{"screenshot":"fe3575ad74c4592c92f1c1d5b1f9b817a3e277a7a3929ba7fdffd6806d675971.png","timeStamp":1674582988138}],"result":"SUCCESS","precondition":false,"level":0},{"number":2,"description":"Cuando seleciona el boton aceptar","duration":73987,"startTime":"2023-01-24T12:56:28.145224800-05:00[America/Bogota]","screenshots":[{"screenshot":"fe3575ad74c4592c92f1c1d5b1f9b817a3e277a7a3929ba7fdffd6806d675971.png","timeStamp":1674582988179}],"exception":{"errorType":"net.thucydides.core.webdriver.exceptions.ElementShouldBeEnabledException","message":"Expected enabled element was not enabled","stackTrace":[{"classLoaderName":"app","declaringClass":"testing.sqa.tasks.SegundoCambio","methodName":"performAs","fileName":"SegundoCambio.java","lineNumber":18,"format":1},{"classLoaderName":"app","declaringClass":"stepdefinitions.SegundoCambioAppsStepDefinitions","methodName":"selecionaElBotonAceptar","fileName":"SegundoCambioAppsStepDefinitions.java","lineNumber":27,"format":1},{"classLoaderName":"app","declaringClass":"cucumber.runner.Runner","methodName":"runPickle","fileName":"Runner.java","lineNumber":80,"format":1},{"classLoaderName":"app","declaringClass":"worker.org.gradle.process.internal.worker.GradleWorkerMain","methodName":"run","fileName":"GradleWorkerMain.java","lineNumber":69,"format":1},{"classLoaderName":"app","declaringClass":"worker.org.gradle.process.internal.worker.GradleWorkerMain","methodName":"main","fileName":"GradleWorkerMain.java","lineNumber":74,"format":1}],"rootCause":{"errorType":"org.openqa.selenium.TimeoutException","message":"Expected condition failed: waiting for By.xpath: //hierarchy/android.widget.FrameLayout/android.widget.LinearLayout/android.widget.FrameLayout/android.widget.LinearLayout/android.widget.FrameLayout/android.webkit.WebView/android.webkit.WebView/android.view.View/android.view.View/android.view.View/android.view.View/android.view.View/android.view.View/android.view.View/android.view.View/android.view.View/android.view.View[2]/android.view.View/android.view.View[2]/android.view.View[2]/android.view.View/android.view.View/android.view.View[1]/android.view.View[1]/android.view.View/android.view.View to be enabled (tried for 5 second(s) with 100 milliseconds interval)","stackTrace":[{"classLoaderName":"app","declaringClass":"testing.sqa.tasks.SegundoCambio","methodName":"performAs","fileName":"SegundoCambio.java","lineNumber":18,"format":1},{"classLoaderName":"app","declaringClass":"stepdefinitions.SegundoCambioAppsStepDefinitions","methodName":"selecionaElBotonAceptar","fileName":"SegundoCambioAppsStepDefinitions.java","lineNumber":27,"format":1},{"classLoaderName":"app","declaringClass":"cucumber.runner.Runner","methodName":"runPickle","fileName":"Runner.java","lineNumber":80,"format":1},{"classLoaderName":"app","declaringClass":"worker.org.gradle.process.internal.worker.GradleWorkerMain","methodName":"run","fileName":"GradleWorkerMain.java","lineNumber":69,"format":1},{"classLoaderName":"app","declaringClass":"worker.org.gradle.process.internal.worker.GradleWorkerMain","methodName":"main","fileName":"GradleWorkerMain.java","lineNumber":74,"format":1}],"rootCause":{"errorType":"org.openqa.selenium.NoSuchElementException","message":"An element could not be located on the page using the given search parameters.\nFor documentation on this error, please visit: https://www.seleniumhq.org/exceptions/no_such_element.html\nBuild info: version: \u00273.141.59\u0027, revision: \u0027e82be7d358\u0027, time: \u00272018-11-14T08:17:03\u0027\nSystem info: host: \u0027SQAMED-88970\u0027, ip: \u002710.201.243.91\u0027, os.name: \u0027Windows 10\u0027, os.arch: \u0027amd64\u0027, os.version: \u002710.0\u0027, java.version: \u002711.0.15.1\u0027\nDriver info: io.appium.java_client.AppiumDriver\nCapabilities {appActivity: .MainActivity, appPackage: movistar.android.app, databaseEnabled: false, desired: {appActivity: .MainActivity, appPackage: movistar.android.app, deviceName: SM-G610M, enableMultiWindows: true, noReset: true, platformName: android, platformVersion: 8.1.0, udid: 52039125ee3064fb}, deviceApiLevel: 27, deviceManufacturer: samsung, deviceModel: SM-G610M, deviceName: 52039125ee3064fb, deviceScreenDensity: 480, deviceScreenSize: 1080x1920, deviceUDID: 52039125ee3064fb, enableMultiWindows: true, javascriptEnabled: true, locationContextEnabled: false, networkConnectionEnabled: true, noReset: true, pixelRatio: 3, platform: LINUX, platformName: Android, platformVersion: 8.1.0, statBarHeight: 72, takesScreenshot: true, udid: 52039125ee3064fb, viewportRect: {height: 1848, left: 0, top: 72, width: 1080}, warnings: {}, webStorageEnabled: false}\nSession ID: c7833b42-0962-406c-b2e6-38fd22dae330\n*** Element info: {Using\u003dxpath, value\u003d//hierarchy/android.widget.FrameLayout/android.widget.LinearLayout/android.widget.FrameLayout/android.widget.LinearLayout/android.widget.FrameLayout/android.webkit.WebView/android.webkit.WebView/android.view.View/android.view.View/android.view.View/android.view.View/android.view.View/android.view.View/android.view.View/android.view.View/android.view.View/android.view.View[2]/android.view.View/android.view.View[2]/android.view.View[2]/android.view.View/android.view.View/android.view.View[1]/android.view.View[1]/android.view.View/android.view.View}","stackTrace":[{"classLoaderName":"app","declaringClass":"io.appium.java_client.remote.AppiumCommandExecutor","methodName":"execute","fileName":"AppiumCommandExecutor.java","lineNumber":247,"format":1},{"classLoaderName":"app","declaringClass":"io.appium.java_client.DefaultGenericMobileDriver","methodName":"execute","fileName":"DefaultGenericMobileDriver.java","lineNumber":41,"format":1},{"classLoaderName":"app","declaringClass":"io.appium.java_client.AppiumDriver","methodName":"execute","fileName":"AppiumDriver.java","lineNumber":1,"format":1},{"classLoaderName":"app","declaringClass":"io.appium.java_client.DefaultGenericMobileDriver","methodName":"findElement","fileName":"DefaultGenericMobileDriver.java","lineNumber":61,"format":1},{"classLoaderName":"app","declaringClass":"io.appium.java_client.AppiumDriver","methodName":"findElement","fileName":"AppiumDriver.java","lineNumber":1,"format":1},{"classLoaderName":"app","declaringClass":"io.appium.java_client.DefaultGenericMobileDriver","methodName":"findElementByXPath","fileName":"DefaultGenericMobileDriver.java","lineNumber":151,"format":1},{"classLoaderName":"app","declaringClass":"io.appium.java_client.AppiumDriver","methodName":"findElementByXPath","fileName":"AppiumDriver.java","lineNumber":1,"format":1},{"classLoaderName":"app","declaringClass":"io.appium.java_client.DefaultGenericMobileDriver","methodName":"findElement","fileName":"DefaultGenericMobileDriver.java","lineNumber":57,"format":1},{"classLoaderName":"app","declaringClass":"io.appium.java_client.AppiumDriver","methodName":"findElement","fileName":"AppiumDriver.java","lineNumber":1,"format":1},{"classLoaderName":"app","declaringClass":"testing.sqa.tasks.SegundoCambio","methodName":"performAs","fileName":"SegundoCambio.java","lineNumber":18,"format":1},{"classLoaderName":"app","declaringClass":"stepdefinitions.SegundoCambioAppsStepDefinitions","methodName":"selecionaElBotonAceptar","fileName":"SegundoCambioAppsStepDefinitions.java","lineNumber":27,"format":1},{"classLoaderName":"app","declaringClass":"cucumber.runner.Runner","methodName":"runPickle","fileName":"Runner.java","lineNumber":80,"format":1},{"classLoaderName":"app","declaringClass":"worker.org.gradle.process.internal.worker.GradleWorkerMain","methodName":"run","fileName":"GradleWorkerMain.java","lineNumber":69,"format":1},{"classLoaderName":"app","declaringClass":"worker.org.gradle.process.internal.worker.GradleWorkerMain","methodName":"main","fileName":"GradleWorkerMain.java","lineNumber":74,"format":1}]}}},"result":"FAILURE","precondition":false,"level":0,"children":[{"number":3,"description":" segundo cambio","duration":73583,"startTime":"2023-01-24T12:56:28.516253100-05:00[America/Bogota]","screenshots":[{"screenshot":"a129a19b4ef5650e2145f1f4a10ea98a5bfacec09048df1020574694e2e334b4.png","timeStamp":1674582989677}],"exception":{"errorType":"net.thucydides.core.webdriver.exceptions.ElementShouldBeEnabledException","message":"Expected enabled element was not enabled","stackTrace":[{"classLoaderName":"app","declaringClass":"testing.sqa.tasks.SegundoCambio","methodName":"performAs","fileName":"SegundoCambio.java","lineNumber":18,"format":1},{"classLoaderName":"app","declaringClass":"stepdefinitions.SegundoCambioAppsStepDefinitions","methodName":"selecionaElBotonAceptar","fileName":"SegundoCambioAppsStepDefinitions.java","lineNumber":27,"format":1},{"classLoaderName":"app","declaringClass":"cucumber.runner.Runner","methodName":"runPickle","fileName":"Runner.java","lineNumber":80,"format":1},{"classLoaderName":"app","declaringClass":"worker.org.gradle.process.internal.worker.GradleWorkerMain","methodName":"run","fileName":"GradleWorkerMain.java","lineNumber":69,"format":1},{"classLoaderName":"app","declaringClass":"worker.org.gradle.process.internal.worker.GradleWorkerMain","methodName":"main","fileName":"GradleWorkerMain.java","lineNumber":74,"format":1}],"rootCause":{"errorType":"org.openqa.selenium.TimeoutException","message":"Expected condition failed: waiting for By.xpath: //hierarchy/android.widget.FrameLayout/android.widget.LinearLayout/android.widget.FrameLayout/android.widget.LinearLayout/android.widget.FrameLayout/android.webkit.WebView/android.webkit.WebView/android.view.View/android.view.View/android.view.View/android.view.View/android.view.View/android.view.View/android.view.View/android.view.View/android.view.View/android.view.View[2]/android.view.View/android.view.View[2]/android.view.View[2]/android.view.View/android.view.View/android.view.View[1]/android.view.View[1]/android.view.View/android.view.View to be enabled (tried for 5 second(s) with 100 milliseconds interval)","stackTrace":[{"classLoaderName":"app","declaringClass":"testing.sqa.tasks.SegundoCambio","methodName":"performAs","fileName":"SegundoCambio.java","lineNumber":18,"format":1},{"classLoaderName":"app","declaringClass":"stepdefinitions.SegundoCambioAppsStepDefinitions","methodName":"selecionaElBotonAceptar","fileName":"SegundoCambioAppsStepDefinitions.java","lineNumber":27,"format":1},{"classLoaderName":"app","declaringClass":"cucumber.runner.Runner","methodName":"runPickle","fileName":"Runner.java","lineNumber":80,"format":1},{"classLoaderName":"app","declaringClass":"worker.org.gradle.process.internal.worker.GradleWorkerMain","methodName":"run","fileName":"GradleWorkerMain.java","lineNumber":69,"format":1},{"classLoaderName":"app","declaringClass":"worker.org.gradle.process.internal.worker.GradleWorkerMain","methodName":"main","fileName":"GradleWorkerMain.java","lineNumber":74,"format":1}],"rootCause":{"errorType":"org.openqa.selenium.NoSuchElementException","message":"An element could not be located on the page using the given search parameters.\nFor documentation on this error, please visit: https://www.seleniumhq.org/exceptions/no_such_element.html\nBuild info: version: \u00273.141.59\u0027, revision: \u0027e82be7d358\u0027, time: \u00272018-11-14T08:17:03\u0027\nSystem info: host: \u0027SQAMED-88970\u0027, ip: \u002710.201.243.91\u0027, os.name: \u0027Windows 10\u0027, os.arch: \u0027amd64\u0027, os.version: \u002710.0\u0027, java.version: \u002711.0.15.1\u0027\nDriver info: io.appium.java_client.AppiumDriver\nCapabilities {appActivity: .MainActivity, appPackage: movistar.android.app, databaseEnabled: false, desired: {appActivity: .MainActivity, appPackage: movistar.android.app, deviceName: SM-G610M, enableMultiWindows: true, noReset: true, platformName: android, platformVersion: 8.1.0, udid: 52039125ee3064fb}, deviceApiLevel: 27, deviceManufacturer: samsung, deviceModel: SM-G610M, deviceName: 52039125ee3064fb, deviceScreenDensity: 480, deviceScreenSize: 1080x1920, deviceUDID: 52039125ee3064fb, enableMultiWindows: true, javascriptEnabled: true, locationContextEnabled: false, networkConnectionEnabled: true, noReset: true, pixelRatio: 3, platform: LINUX, platformName: Android, platformVersion: 8.1.0, statBarHeight: 72, takesScreenshot: true, udid: 52039125ee3064fb, viewportRect: {height: 1848, left: 0, top: 72, width: 1080}, warnings: {}, webStorageEnabled: false}\nSession ID: c7833b42-0962-406c-b2e6-38fd22dae330\n*** Element info: {Using\u003dxpath, value\u003d//hierarchy/android.widget.FrameLayout/android.widget.LinearLayout/android.widget.FrameLayout/android.widget.LinearLayout/android.widget.FrameLayout/android.webkit.WebView/android.webkit.WebView/android.view.View/android.view.View/android.view.View/android.view.View/android.view.View/android.view.View/android.view.View/android.view.View/android.view.View/android.view.View[2]/android.view.View/android.view.View[2]/android.view.View[2]/android.view.View/android.view.View/android.view.View[1]/android.view.View[1]/android.view.View/android.view.View}","stackTrace":[{"classLoaderName":"app","declaringClass":"io.appium.java_client.remote.AppiumCommandExecutor","methodName":"execute","fileName":"AppiumCommandExecutor.java","lineNumber":247,"format":1},{"classLoaderName":"app","declaringClass":"io.appium.java_client.DefaultGenericMobileDriver","methodName":"execute","fileName":"DefaultGenericMobileDriver.java","lineNumber":41,"format":1},{"classLoaderName":"app","declaringClass":"io.appium.java_client.AppiumDriver","methodName":"execute","fileName":"AppiumDriver.java","lineNumber":1,"format":1},{"classLoaderName":"app","declaringClass":"io.appium.java_client.DefaultGenericMobileDriver","methodName":"findElement","fileName":"DefaultGenericMobileDriver.java","lineNumber":61,"format":1},{"classLoaderName":"app","declaringClass":"io.appium.java_client.AppiumDriver","methodName":"findElement","fileName":"AppiumDriver.java","lineNumber":1,"format":1},{"classLoaderName":"app","declaringClass":"io.appium.java_client.DefaultGenericMobileDriver","methodName":"findElementByXPath","fileName":"DefaultGenericMobileDriver.java","lineNumber":151,"format":1},{"classLoaderName":"app","declaringClass":"io.appium.java_client.AppiumDriver","methodName":"findElementByXPath","fileName":"AppiumDriver.java","lineNumber":1,"format":1},{"classLoaderName":"app","declaringClass":"io.appium.java_client.DefaultGenericMobileDriver","methodName":"findElement","fileName":"DefaultGenericMobileDriver.java","lineNumber":57,"format":1},{"classLoaderName":"app","declaringClass":"io.appium.java_client.AppiumDriver","methodName":"findElement","fileName":"AppiumDriver.java","lineNumber":1,"format":1},{"classLoaderName":"app","declaringClass":"testing.sqa.tasks.SegundoCambio","methodName":"performAs","fileName":"SegundoCambio.java","lineNumber":18,"format":1},{"classLoaderName":"app","declaringClass":"stepdefinitions.SegundoCambioAppsStepDefinitions","methodName":"selecionaElBotonAceptar","fileName":"SegundoCambioAppsStepDefinitions.java","lineNumber":27,"format":1},{"classLoaderName":"app","declaringClass":"cucumber.runner.Runner","methodName":"runPickle","fileName":"Runner.java","lineNumber":80,"format":1},{"classLoaderName":"app","declaringClass":"worker.org.gradle.process.internal.worker.GradleWorkerMain","methodName":"run","fileName":"GradleWorkerMain.java","lineNumber":69,"format":1},{"classLoaderName":"app","declaringClass":"worker.org.gradle.process.internal.worker.GradleWorkerMain","methodName":"main","fileName":"GradleWorkerMain.java","lineNumber":74,"format":1}]}}},"result":"FAILURE","precondition":false,"level":1,"children":[{"number":4,"description":" explicit wait","duration":12334,"startTime":"2023-01-24T12:56:29.822350300-05:00[America/Bogota]","screenshots":[{"screenshot":"0c69fd1d63ad1adea179a6e9bfe4b5ed5ee78633ea9a03f5bc86397d4fab51bf.png","timeStamp":1674582991002},{"screenshot":"148112b9481df347d9389f98111d6977041169980cac7a2d188d96ca749df5e3.png","timeStamp":1674583002156}],"result":"SUCCESS","precondition":false,"level":2},{"number":5,"description":" clicks on lista desplegable con las lineas a usar","duration":5473,"startTime":"2023-01-24T12:56:42.173301700-05:00[America/Bogota]","screenshots":[{"screenshot":"5696ac163492d60d51f903a0faaccc16b7dcb88f5e9ada557e4d576c36695aee.png","timeStamp":1674583003289},{"screenshot":"1a1c879852b1c851aec7c78b0911dcc4eb57f62b3240ece6b071ee7cd17dbcf7.png","timeStamp":1674583007646}],"result":"SUCCESS","precondition":false,"level":2},{"number":6,"description":" scroll down","duration":11840,"startTime":"2023-01-24T12:56:47.650775400-05:00[America/Bogota]","screenshots":[{"screenshot":"1a1c879852b1c851aec7c78b0911dcc4eb57f62b3240ece6b071ee7cd17dbcf7.png","timeStamp":1674583007682},{"screenshot":"5a96551adc85919ff7f7c27d51c257fe7b80d52a17d7c42ac9d99eae601de61a.png","timeStamp":1674583019491}],"result":"SUCCESS","precondition":false,"level":2},{"number":7,"description":" scroll up","duration":6693,"startTime":"2023-01-24T12:56:59.494621900-05:00[America/Bogota]","screenshots":[{"screenshot":"5a96551adc85919ff7f7c27d51c257fe7b80d52a17d7c42ac9d99eae601de61a.png","timeStamp":1674583019525},{"screenshot":"7b0d4d55a67ac76009d7e9280f296e1f057eebcaa7681d1631db0e43d5cf968a.png","timeStamp":1674583026188}],"result":"SUCCESS","precondition":false,"level":2},{"number":8,"description":" explicit wait","duration":11204,"startTime":"2023-01-24T12:57:06.191124200-05:00[America/Bogota]","screenshots":[{"screenshot":"7b0d4d55a67ac76009d7e9280f296e1f057eebcaa7681d1631db0e43d5cf968a.png","timeStamp":1674583026219},{"screenshot":"93d0cd988394c74d6a7d05a7c7fcbb96ef9c53a636a75efea87ea7a9df5d141c.png","timeStamp":1674583037394}],"result":"SUCCESS","precondition":false,"level":2},{"number":9,"description":" clicks on linea a seleccionar","duration":2726,"startTime":"2023-01-24T12:57:17.398483900-05:00[America/Bogota]","screenshots":[{"screenshot":"93d0cd988394c74d6a7d05a7c7fcbb96ef9c53a636a75efea87ea7a9df5d141c.png","timeStamp":1674583037422},{"screenshot":"a3bceb6ca2fa78dc02207eb5c8d38062e7a40ba32321c989333b50a7a554bc75.png","timeStamp":1674583040124}],"result":"SUCCESS","precondition":false,"level":2},{"number":10,"description":" explicit wait","duration":11090,"startTime":"2023-01-24T12:57:20.126683700-05:00[America/Bogota]","screenshots":[{"screenshot":"a3bceb6ca2fa78dc02207eb5c8d38062e7a40ba32321c989333b50a7a554bc75.png","timeStamp":1674583040146},{"screenshot":"3fe71ddd00aed045507bad98ea60ae7527cdf7e8b302177ecfb91894fd81f675.png","timeStamp":1674583051217}],"result":"SUCCESS","precondition":false,"level":2},{"number":11,"description":" scroll down","duration":2976,"startTime":"2023-01-24T12:57:31.219509900-05:00[America/Bogota]","screenshots":[{"screenshot":"3fe71ddd00aed045507bad98ea60ae7527cdf7e8b302177ecfb91894fd81f675.png","timeStamp":1674583051244},{"screenshot":"3fe71ddd00aed045507bad98ea60ae7527cdf7e8b302177ecfb91894fd81f675.png","timeStamp":1674583054195}],"result":"SUCCESS","precondition":false,"level":2},{"number":12,"description":" clicks on botton elegiapps","duration":7875,"startTime":"2023-01-24T12:57:34.198730600-05:00[America/Bogota]","screenshots":[{"screenshot":"3fe71ddd00aed045507bad98ea60ae7527cdf7e8b302177ecfb91894fd81f675.png","timeStamp":1674583054227},{"screenshot":"3fe71ddd00aed045507bad98ea60ae7527cdf7e8b302177ecfb91894fd81f675.png","htmlSource":"pagesource11061645507259176600.html.txt","timeStamp":1674583062060}],"exception":{"errorType":"net.thucydides.core.webdriver.exceptions.ElementShouldBeEnabledException","message":"Expected enabled element was not enabled","stackTrace":[{"classLoaderName":"app","declaringClass":"testing.sqa.tasks.SegundoCambio","methodName":"performAs","fileName":"SegundoCambio.java","lineNumber":18,"format":1},{"classLoaderName":"app","declaringClass":"stepdefinitions.SegundoCambioAppsStepDefinitions","methodName":"selecionaElBotonAceptar","fileName":"SegundoCambioAppsStepDefinitions.java","lineNumber":27,"format":1},{"classLoaderName":"app","declaringClass":"cucumber.runner.Runner","methodName":"runPickle","fileName":"Runner.java","lineNumber":80,"format":1},{"classLoaderName":"app","declaringClass":"worker.org.gradle.process.internal.worker.GradleWorkerMain","methodName":"run","fileName":"GradleWorkerMain.java","lineNumber":69,"format":1},{"classLoaderName":"app","declaringClass":"worker.org.gradle.process.internal.worker.GradleWorkerMain","methodName":"main","fileName":"GradleWorkerMain.java","lineNumber":74,"format":1}],"rootCause":{"errorType":"org.openqa.selenium.TimeoutException","message":"Expected condition failed: waiting for By.xpath: //hierarchy/android.widget.FrameLayout/android.widget.LinearLayout/android.widget.FrameLayout/android.widget.LinearLayout/android.widget.FrameLayout/android.webkit.WebView/android.webkit.WebView/android.view.View/android.view.View/android.view.View/android.view.View/android.view.View/android.view.View/android.view.View/android.view.View/android.view.View/android.view.View[2]/android.view.View/android.view.View[2]/android.view.View[2]/android.view.View/android.view.View/android.view.View[1]/android.view.View[1]/android.view.View/android.view.View to be enabled (tried for 5 second(s) with 100 milliseconds interval)","stackTrace":[{"classLoaderName":"app","declaringClass":"testing.sqa.tasks.SegundoCambio","methodName":"performAs","fileName":"SegundoCambio.java","lineNumber":18,"format":1},{"classLoaderName":"app","declaringClass":"stepdefinitions.SegundoCambioAppsStepDefinitions","methodName":"selecionaElBotonAceptar","fileName":"SegundoCambioAppsStepDefinitions.java","lineNumber":27,"format":1},{"classLoaderName":"app","declaringClass":"cucumber.runner.Runner","methodName":"runPickle","fileName":"Runner.java","lineNumber":80,"format":1},{"classLoaderName":"app","declaringClass":"worker.org.gradle.process.internal.worker.GradleWorkerMain","methodName":"run","fileName":"GradleWorkerMain.java","lineNumber":69,"format":1},{"classLoaderName":"app","declaringClass":"worker.org.gradle.process.internal.worker.GradleWorkerMain","methodName":"main","fileName":"GradleWorkerMain.java","lineNumber":74,"format":1}],"rootCause":{"errorType":"org.openqa.selenium.NoSuchElementException","message":"An element could not be located on the page using the given search parameters.\nFor documentation on this error, please visit: https://www.seleniumhq.org/exceptions/no_such_element.html\nBuild info: version: \u00273.141.59\u0027, revision: \u0027e82be7d358\u0027, time: \u00272018-11-14T08:17:03\u0027\nSystem info: host: \u0027SQAMED-88970\u0027, ip: \u002710.201.243.91\u0027, os.name: \u0027Windows 10\u0027, os.arch: \u0027amd64\u0027, os.version: \u002710.0\u0027, java.version: \u002711.0.15.1\u0027\nDriver info: io.appium.java_client.AppiumDriver\nCapabilities {appActivity: .MainActivity, appPackage: movistar.android.app, databaseEnabled: false, desired: {appActivity: .MainActivity, appPackage: movistar.android.app, deviceName: SM-G610M, enableMultiWindows: true, noReset: true, platformName: android, platformVersion: 8.1.0, udid: 52039125ee3064fb}, deviceApiLevel: 27, deviceManufacturer: samsung, deviceModel: SM-G610M, deviceName: 52039125ee3064fb, deviceScreenDensity: 480, deviceScreenSize: 1080x1920, deviceUDID: 52039125ee3064fb, enableMultiWindows: true, javascriptEnabled: true, locationContextEnabled: false, networkConnectionEnabled: true, noReset: true, pixelRatio: 3, platform: LINUX, platformName: Android, platformVersion: 8.1.0, statBarHeight: 72, takesScreenshot: true, udid: 52039125ee3064fb, viewportRect: {height: 1848, left: 0, top: 72, width: 1080}, warnings: {}, webStorageEnabled: false}\nSession ID: c7833b42-0962-406c-b2e6-38fd22dae330\n*** Element info: {Using\u003dxpath, value\u003d//hierarchy/android.widget.FrameLayout/android.widget.LinearLayout/android.widget.FrameLayout/android.widget.LinearLayout/android.widget.FrameLayout/android.webkit.WebView/android.webkit.WebView/android.view.View/android.view.View/android.view.View/android.view.View/android.view.View/android.view.View/android.view.View/android.view.View/android.view.View/android.view.View[2]/android.view.View/android.view.View[2]/android.view.View[2]/android.view.View/android.view.View/android.view.View[1]/android.view.View[1]/android.view.View/android.view.View}","stackTrace":[{"classLoaderName":"app","declaringClass":"io.appium.java_client.remote.AppiumCommandExecutor","methodName":"execute","fileName":"AppiumCommandExecutor.java","lineNumber":247,"format":1},{"classLoaderName":"app","declaringClass":"io.appium.java_client.DefaultGenericMobileDriver","methodName":"execute","fileName":"DefaultGenericMobileDriver.java","lineNumber":41,"format":1},{"classLoaderName":"app","declaringClass":"io.appium.java_client.AppiumDriver","methodName":"execute","fileName":"AppiumDriver.java","lineNumber":1,"format":1},{"classLoaderName":"app","declaringClass":"io.appium.java_client.DefaultGenericMobileDriver","methodName":"findElement","fileName":"DefaultGenericMobileDriver.java","lineNumber":61,"format":1},{"classLoaderName":"app","declaringClass":"io.appium.java_client.AppiumDriver","methodName":"findElement","fileName":"AppiumDriver.java","lineNumber":1,"format":1},{"classLoaderName":"app","declaringClass":"io.appium.java_client.DefaultGenericMobileDriver","methodName":"findElementByXPath","fileName":"DefaultGenericMobileDriver.java","lineNumber":151,"format":1},{"classLoaderName":"app","declaringClass":"io.appium.java_client.AppiumDriver","methodName":"findElementByXPath","fileName":"AppiumDriver.java","lineNumber":1,"format":1},{"classLoaderName":"app","declaringClass":"io.appium.java_client.DefaultGenericMobileDriver","methodName":"findElement","fileName":"DefaultGenericMobileDriver.java","lineNumber":57,"format":1},{"classLoaderName":"app","declaringClass":"io.appium.java_client.AppiumDriver","methodName":"findElement","fileName":"AppiumDriver.java","lineNumber":1,"format":1},{"classLoaderName":"app","declaringClass":"testing.sqa.tasks.SegundoCambio","methodName":"performAs","fileName":"SegundoCambio.java","lineNumber":18,"format":1},{"classLoaderName":"app","declaringClass":"stepdefinitions.SegundoCambioAppsStepDefinitions","methodName":"selecionaElBotonAceptar","fileName":"SegundoCambioAppsStepDefinitions.java","lineNumber":27,"format":1},{"classLoaderName":"app","declaringClass":"cucumber.runner.Runner","methodName":"runPickle","fileName":"Runner.java","lineNumber":80,"format":1},{"classLoaderName":"app","declaringClass":"worker.org.gradle.process.internal.worker.GradleWorkerMain","methodName":"run","fileName":"GradleWorkerMain.java","lineNumber":69,"format":1},{"classLoaderName":"app","declaringClass":"worker.org.gradle.process.internal.worker.GradleWorkerMain","methodName":"main","fileName":"GradleWorkerMain.java","lineNumber":74,"format":1}]}}},"result":"FAILURE","precondition":false,"level":2}]}]},{"number":13,"description":"Entonces la modificcacion de las apps sea exitosa","duration":35,"startTime":"2023-01-24T12:57:42.192326500-05:00[America/Bogota]","result":"SKIPPED","precondition":false,"level":0}],"userStory":{"id":"segundo-cambio-de-apps","storyName":"Segundo cambio de apps","path":"src/test/resources/features/SegundoCambioApps.feature","type":"feature"},"featureTag":{"name":"Features/Segundo cambio de apps","type":"feature","displayName":"Features/Segundo cambio de apps"},"title":"validar  segundo cambio  de apps $4990","tags":[{"name":"SegundoCambioApps","type":"tag","displayName":"SegundoCambioApps"},{"name":"Segundo cambio de apps","type":"feature","displayName":"Segundo cambio de apps"}],"startTime":"2023-01-24T12:56:08.487457700-05:00[America/Bogota]","duration":93746,"testFailureCause":{"errorType":"net.thucydides.core.webdriver.exceptions.ElementShouldBeEnabledException","message":"Expected enabled element was not enabled","stackTrace":[{"classLoaderName":"app","declaringClass":"testing.sqa.tasks.SegundoCambio","methodName":"performAs","fileName":"SegundoCambio.java","lineNumber":18,"format":1},{"classLoaderName":"app","declaringClass":"stepdefinitions.SegundoCambioAppsStepDefinitions","methodName":"selecionaElBotonAceptar","fileName":"SegundoCambioAppsStepDefinitions.java","lineNumber":27,"format":1},{"classLoaderName":"app","declaringClass":"cucumber.runner.Runner","methodName":"runPickle","fileName":"Runner.java","lineNumber":80,"format":1},{"classLoaderName":"app","declaringClass":"worker.org.gradle.process.internal.worker.GradleWorkerMain","methodName":"run","fileName":"GradleWorkerMain.java","lineNumber":69,"format":1},{"classLoaderName":"app","declaringClass":"worker.org.gradle.process.internal.worker.GradleWorkerMain","methodName":"main","fileName":"GradleWorkerMain.java","lineNumber":74,"format":1}],"rootCause":{"errorType":"org.openqa.selenium.TimeoutException","message":"Expected condition failed: waiting for By.xpath: //hierarchy/android.widget.FrameLayout/android.widget.LinearLayout/android.widget.FrameLayout/android.widget.LinearLayout/android.widget.FrameLayout/android.webkit.WebView/android.webkit.WebView/android.view.View/android.view.View/android.view.View/android.view.View/android.view.View/android.view.View/android.view.View/android.view.View/android.view.View/android.view.View[2]/android.view.View/android.view.View[2]/android.view.View[2]/android.view.View/android.view.View/android.view.View[1]/android.view.View[1]/android.view.View/android.view.View to be enabled (tried for 5 second(s) with 100 milliseconds interval)","stackTrace":[{"classLoaderName":"app","declaringClass":"testing.sqa.tasks.SegundoCambio","methodName":"performAs","fileName":"SegundoCambio.java","lineNumber":18,"format":1},{"classLoaderName":"app","declaringClass":"stepdefinitions.SegundoCambioAppsStepDefinitions","methodName":"selecionaElBotonAceptar","fileName":"SegundoCambioAppsStepDefinitions.java","lineNumber":27,"format":1},{"classLoaderName":"app","declaringClass":"cucumber.runner.Runner","methodName":"runPickle","fileName":"Runner.java","lineNumber":80,"format":1},{"classLoaderName":"app","declaringClass":"worker.org.gradle.process.internal.worker.GradleWorkerMain","methodName":"run","fileName":"GradleWorkerMain.java","lineNumber":69,"format":1},{"classLoaderName":"app","declaringClass":"worker.org.gradle.process.internal.worker.GradleWorkerMain","methodName":"main","fileName":"GradleWorkerMain.java","lineNumber":74,"format":1}],"rootCause":{"errorType":"org.openqa.selenium.NoSuchElementException","message":"An element could not be located on the page using the given search parameters.\nFor documentation on this error, please visit: https://www.seleniumhq.org/exceptions/no_such_element.html\nBuild info: version: \u00273.141.59\u0027, revision: \u0027e82be7d358\u0027, time: \u00272018-11-14T08:17:03\u0027\nSystem info: host: \u0027SQAMED-88970\u0027, ip: \u002710.201.243.91\u0027, os.name: \u0027Windows 10\u0027, os.arch: \u0027amd64\u0027, os.version: \u002710.0\u0027, java.version: \u002711.0.15.1\u0027\nDriver info: io.appium.java_client.AppiumDriver\nCapabilities {appActivity: .MainActivity, appPackage: movistar.android.app, databaseEnabled: false, desired: {appActivity: .MainActivity, appPackage: movistar.android.app, deviceName: SM-G610M, enableMultiWindows: true, noReset: true, platformName: android, platformVersion: 8.1.0, udid: 52039125ee3064fb}, deviceApiLevel: 27, deviceManufacturer: samsung, deviceModel: SM-G610M, deviceName: 52039125ee3064fb, deviceScreenDensity: 480, deviceScreenSize: 1080x1920, deviceUDID: 52039125ee3064fb, enableMultiWindows: true, javascriptEnabled: true, locationContextEnabled: false, networkConnectionEnabled: true, noReset: true, pixelRatio: 3, platform: LINUX, platformName: Android, platformVersion: 8.1.0, statBarHeight: 72, takesScreenshot: true, udid: 52039125ee3064fb, viewportRect: {height: 1848, left: 0, top: 72, width: 1080}, warnings: {}, webStorageEnabled: false}\nSession ID: c7833b42-0962-406c-b2e6-38fd22dae330\n*** Element info: {Using\u003dxpath, value\u003d//hierarchy/android.widget.FrameLayout/android.widget.LinearLayout/android.widget.FrameLayout/android.widget.LinearLayout/android.widget.FrameLayout/android.webkit.WebView/android.webkit.WebView/android.view.View/android.view.View/android.view.View/android.view.View/android.view.View/android.view.View/android.view.View/android.view.View/android.view.View/android.view.View[2]/android.view.View/android.view.View[2]/android.view.View[2]/android.view.View/android.view.View/android.view.View[1]/android.view.View[1]/android.view.View/android.view.View}","stackTrace":[{"classLoaderName":"app","declaringClass":"io.appium.java_client.remote.AppiumCommandExecutor","methodName":"execute","fileName":"AppiumCommandExecutor.java","lineNumber":247,"format":1},{"classLoaderName":"app","declaringClass":"io.appium.java_client.DefaultGenericMobileDriver","methodName":"execute","fileName":"DefaultGenericMobileDriver.java","lineNumber":41,"format":1},{"classLoaderName":"app","declaringClass":"io.appium.java_client.AppiumDriver","methodName":"execute","fileName":"AppiumDriver.java","lineNumber":1,"format":1},{"classLoaderName":"app","declaringClass":"io.appium.java_client.DefaultGenericMobileDriver","methodName":"findElement","fileName":"DefaultGenericMobileDriver.java","lineNumber":61,"format":1},{"classLoaderName":"app","declaringClass":"io.appium.java_client.AppiumDriver","methodName":"findElement","fileName":"AppiumDriver.java","lineNumber":1,"format":1},{"classLoaderName":"app","declaringClass":"io.appium.java_client.DefaultGenericMobileDriver","methodName":"findElementByXPath","fileName":"DefaultGenericMobileDriver.java","lineNumber":151,"format":1},{"classLoaderName":"app","declaringClass":"io.appium.java_client.AppiumDriver","methodName":"findElementByXPath","fileName":"AppiumDriver.java","lineNumber":1,"format":1},{"classLoaderName":"app","declaringClass":"io.appium.java_client.DefaultGenericMobileDriver","methodName":"findElement","fileName":"DefaultGenericMobileDriver.java","lineNumber":57,"format":1},{"classLoaderName":"app","declaringClass":"io.appium.java_client.AppiumDriver","methodName":"findElement","fileName":"AppiumDriver.java","lineNumber":1,"format":1},{"classLoaderName":"app","declaringClass":"testing.sqa.tasks.SegundoCambio","methodName":"performAs","fileName":"SegundoCambio.java","lineNumber":18,"format":1},{"classLoaderName":"app","declaringClass":"stepdefinitions.SegundoCambioAppsStepDefinitions","methodName":"selecionaElBotonAceptar","fileName":"SegundoCambioAppsStepDefinitions.java","lineNumber":27,"format":1},{"classLoaderName":"app","declaringClass":"cucumber.runner.Runner","methodName":"runPickle","fileName":"Runner.java","lineNumber":80,"format":1},{"classLoaderName":"app","declaringClass":"worker.org.gradle.process.internal.worker.GradleWorkerMain","methodName":"run","fileName":"GradleWorkerMain.java","lineNumber":69,"format":1},{"classLoaderName":"app","declaringClass":"worker.org.gradle.process.internal.worker.GradleWorkerMain","methodName":"main","fileName":"GradleWorkerMain.java","lineNumber":74,"format":1}]}}},"testFailureClassname":"net.thucydides.core.webdriver.exceptions.ElementShouldBeEnabledException","testFailureMessage":"Expected enabled element was not enabled","testFailureSummary":"FAILURE;net.thucydides.core.webdriver.exceptions.ElementShouldBeEnabledException;Expected enabled element was not enabled;SegundoCambio.java","projectKey":"","annotatedResult":"FAILURE","sessionId":"c7833b42-0962-406c-b2e6-38fd22dae330","driver":"firefox","isManualTestingUpToDate":false,"manual":false,"testSource":"Cucumber","actors":[{"name":"","can":["browse the web"]}],"result":"FAILURE"}